monitax_cli/__init__.py
monitax_cli/config.py
monitax_cli/configure.py
monitax_cli/device.py
monitax_cli/invoice.py
monitax_cli/main.py
monitax_cli/user.py
monitax_cli-0.1.2.dist-info/entry_points.txt
monitax_cli-0.1.2.dist-info/WHEEL
monitax_cli-0.1.2.dist-info/METADATA
monitax_cli-0.1.2.dist-info/RECORD
