Metadata-Version: 2.1
Name: monitax-cli
Version: 0.1.2
Summary: Monitax Client
Author: ekalaya2015
Author-email: ekalaya2015@gmail.com
Requires-Python: >=3.10,<4.0
Classifier: Programming Language :: Python :: 3
Classifier: Programming Language :: Python :: 3.10
Requires-Dist: pathlib (>=1.0.1,<2.0.0)
Requires-Dist: pendulum (>=2.1.2,<3.0.0)
Requires-Dist: requests (>=2.28.1,<3.0.0)
Requires-Dist: typer[all] (>=0.6.1,<0.7.0)
